hypehd/__init__.py
hypehd/data_manipulation.py
hypehd/visualization.py
hypehd/data/demographic.csv
hypehd/data/vital_signs.csv
hypehd-0.1.9.dist-info/LICENSE.md
hypehd-0.1.9.dist-info/METADATA
hypehd-0.1.9.dist-info/WHEEL
hypehd-0.1.9.dist-info/top_level.txt
hypehd-0.1.9.dist-info/RECORD
