Metadata-Version: 2.1
Name: hypehd
Version: 0.1.9
Summary: This package aims to be a tool for real-world and practical data analysis, assisting in reaching a quicker understanding of various health related data.
Home-page: https://github.com/Alieyeh/hypehd
Author: Jiayi Wang, Alieyeh Sarabandi Moghaddam
Author-email: jw1289@exeter.ac.uk, as1724@exeter.ac.uk
License: The MIT License (MIT)
Classifier: Programming Language :: Python :: 3.7
Classifier: License :: OSI Approved :: MIT License
Classifier: Operating System :: OS Independent
Requires-Python: >=3.7
License-File: LICENSE.md
Requires-Dist: numpy (>=1.19.4)
Requires-Dist: matplotlib (>=3.5.3)
Requires-Dist: seaborn (>=0.11.0)
Requires-Dist: pandas (>=1.0.1)
Requires-Dist: scipy (>=1.4.1)
Requires-Dist: scikit-learn (>=0.22.1)
Requires-Dist: lifelines (>=0.27.4)
